clovers_sarof/modules/market/__init__.py
clovers_sarof/modules/market/config.py
clovers_sarof/modules/market/tools.py
clovers_sarof_market-0.1.0.dist-info/METADATA
clovers_sarof_market-0.1.0.dist-info/WHEEL
clovers_sarof_market-0.1.0.dist-info/RECORD
